<?xml version="1.0" encoding="utf-8" ?>
<dwsync>
<file name="bg.php" server="ftp.ekinyazilim.com/public_html/demo/mail/" local="130209238180000000" remote="130314052200000000" Dst="1" />
<file name="ca.php" server="ftp.ekinyazilim.com/public_html/demo/mail/" local="130209238180000000" remote="130314052200000000" Dst="1" />
<file name="cs.php" server="ftp.ekinyazilim.com/public_html/demo/mail/" local="130209238180000000" remote="130314052200000000" Dst="1" />
<file name="cy.php" server="ftp.ekinyazilim.com/public_html/demo/mail/" local="130209238180000000" remote="130314052200000000" Dst="1" />
<file name="da.php" server="ftp.ekinyazilim.com/public_html/demo/mail/" local="130209238180000000" remote="130314052200000000" Dst="1" />
<file name="de.php" server="ftp.ekinyazilim.com/public_html/demo/mail/" local="130209238180000000" remote="130314052200000000" Dst="1" />
<file name="el.php" server="ftp.ekinyazilim.com/public_html/demo/mail/" local="130209238180000000" remote="130314052200000000" Dst="1" />
<file name="en.php" server="ftp.ekinyazilim.com/public_html/demo/mail/" local="130209238180000000" remote="130314052200000000" Dst="1" />
<file name="eo.php" server="ftp.ekinyazilim.com/public_html/demo/mail/" local="130209238180000000" remote="130314052200000000" Dst="1" />
<file name="es-mx.php" server="ftp.ekinyazilim.com/public_html/demo/mail/" local="130209238180000000" remote="130314052200000000" Dst="1" />
<file name="es.php" server="ftp.ekinyazilim.com/public_html/demo/mail/" local="130209238180000000" remote="130314052200000000" Dst="1" />
<file name="et.php" server="ftp.ekinyazilim.com/public_html/demo/mail/" local="130209238180000000" remote="130314052200000000" Dst="1" />
<file name="fa.php" server="ftp.ekinyazilim.com/public_html/demo/mail/" local="130209238180000000" remote="130314052200000000" Dst="1" />
<file name="fi.php" server="ftp.ekinyazilim.com/public_html/demo/mail/" local="130209238180000000" remote="130314052200000000" Dst="1" />
<file name="fr.php" server="ftp.ekinyazilim.com/public_html/demo/mail/" local="130209238180000000" remote="130314052200000000" Dst="1" />
<file name="gu.php" server="ftp.ekinyazilim.com/public_html/demo/mail/" local="130209238180000000" remote="130314052200000000" Dst="1" />
<file name="he.php" server="ftp.ekinyazilim.com/public_html/demo/mail/" local="130209238180000000" remote="130314052200000000" Dst="1" />
<file name="hi.php" server="ftp.ekinyazilim.com/public_html/demo/mail/" local="130209238180000000" remote="130314052200000000" Dst="1" />
<file name="hr.php" server="ftp.ekinyazilim.com/public_html/demo/mail/" local="130209238180000000" remote="130314052200000000" Dst="1" />
<file name="hu.php" server="ftp.ekinyazilim.com/public_html/demo/mail/" local="130209238180000000" remote="130314052200000000" Dst="1" />
<file name="it.php" server="ftp.ekinyazilim.com/public_html/demo/mail/" local="130209238180000000" remote="130314052200000000" Dst="1" />
<file name="ja.php" server="ftp.ekinyazilim.com/public_html/demo/mail/" local="130209238180000000" remote="130314052200000000" Dst="1" />
<file name="lt.php" server="ftp.ekinyazilim.com/public_html/demo/mail/" local="130209238180000000" remote="130314052200000000" Dst="1" />
<file name="lv.php" server="ftp.ekinyazilim.com/public_html/demo/mail/" local="130209238180000000" remote="130314052200000000" Dst="1" />
<file name="nb.php" server="ftp.ekinyazilim.com/public_html/demo/mail/" local="130209238180000000" remote="130314052200000000" Dst="1" />
<file name="nl.php" server="ftp.ekinyazilim.com/public_html/demo/mail/" local="130209238180000000" remote="130314052200000000" Dst="1" />
<file name="nn.php" server="ftp.ekinyazilim.com/public_html/demo/mail/" local="130209238180000000" remote="130314052200000000" Dst="1" />
<file name="no.php" server="ftp.ekinyazilim.com/public_html/demo/mail/" local="130209238180000000" remote="130314052200000000" Dst="1" />
<file name="pl.php" server="ftp.ekinyazilim.com/public_html/demo/mail/" local="130209238180000000" remote="130314052200000000" Dst="1" />
<file name="pt-br.php" server="ftp.ekinyazilim.com/public_html/demo/mail/" local="130209238180000000" remote="130314052200000000" Dst="1" />
<file name="ro.php" server="ftp.ekinyazilim.com/public_html/demo/mail/" local="130209238180000000" remote="130314052200000000" Dst="1" />
<file name="ru.php" server="ftp.ekinyazilim.com/public_html/demo/mail/" local="130209238180000000" remote="130314052200000000" Dst="1" />
<file name="sk.php" server="ftp.ekinyazilim.com/public_html/demo/mail/" local="130209238180000000" remote="130314052200000000" Dst="1" />
<file name="sl.php" server="ftp.ekinyazilim.com/public_html/demo/mail/" local="130209238180000000" remote="130314052200000000" Dst="1" />
<file name="sr.php" server="ftp.ekinyazilim.com/public_html/demo/mail/" local="130209238180000000" remote="130314052200000000" Dst="1" />
<file name="sv.php" server="ftp.ekinyazilim.com/public_html/demo/mail/" local="130209238180000000" remote="130314052200000000" Dst="1" />
<file name="tr.php" server="ftp.ekinyazilim.com/public_html/demo/mail/" local="130209238180000000" remote="130314052200000000" Dst="1" />
<file name="vi.php" server="ftp.ekinyazilim.com/public_html/demo/mail/" local="130209238180000000" remote="130314052200000000" Dst="1" />
<file name="zh-cn.php" server="ftp.ekinyazilim.com/public_html/demo/mail/" local="130209238180000000" remote="130314052200000000" Dst="1" />
<file name="zh-tw.php" server="ftp.ekinyazilim.com/public_html/demo/mail/" local="130209238180000000" remote="130314052200000000" Dst="1" />
<file name="bg.php" server="ftp.ekinyazilim.com/public_html/demo/nurskrom/" local="130209238180000000" remote="130368576600000000" Dst="1" />
<file name="ca.php" server="ftp.ekinyazilim.com/public_html/demo/nurskrom/" local="130209238180000000" remote="130368576600000000" Dst="1" />
<file name="cs.php" server="ftp.ekinyazilim.com/public_html/demo/nurskrom/" local="130209238180000000" remote="130368576600000000" Dst="1" />
<file name="cy.php" server="ftp.ekinyazilim.com/public_html/demo/nurskrom/" local="130209238180000000" remote="130368576600000000" Dst="1" />
<file name="da.php" server="ftp.ekinyazilim.com/public_html/demo/nurskrom/" local="130209238180000000" remote="130368576600000000" Dst="1" />
<file name="de.php" server="ftp.ekinyazilim.com/public_html/demo/nurskrom/" local="130209238180000000" remote="130368576600000000" Dst="1" />
<file name="el.php" server="ftp.ekinyazilim.com/public_html/demo/nurskrom/" local="130209238180000000" remote="130368576600000000" Dst="1" />
<file name="en.php" server="ftp.ekinyazilim.com/public_html/demo/nurskrom/" local="130209238180000000" remote="130368576600000000" Dst="1" />
<file name="eo.php" server="ftp.ekinyazilim.com/public_html/demo/nurskrom/" local="130209238180000000" remote="130368576600000000" Dst="1" />
<file name="es-mx.php" server="ftp.ekinyazilim.com/public_html/demo/nurskrom/" local="130209238180000000" remote="130368576600000000" Dst="1" />
<file name="es.php" server="ftp.ekinyazilim.com/public_html/demo/nurskrom/" local="130209238180000000" remote="130368576600000000" Dst="1" />
<file name="et.php" server="ftp.ekinyazilim.com/public_html/demo/nurskrom/" local="130209238180000000" remote="130368576600000000" Dst="1" />
<file name="fa.php" server="ftp.ekinyazilim.com/public_html/demo/nurskrom/" local="130209238180000000" remote="130368576600000000" Dst="1" />
<file name="fi.php" server="ftp.ekinyazilim.com/public_html/demo/nurskrom/" local="130209238180000000" remote="130368576600000000" Dst="1" />
<file name="fr.php" server="ftp.ekinyazilim.com/public_html/demo/nurskrom/" local="130209238180000000" remote="130368576600000000" Dst="1" />
<file name="gu.php" server="ftp.ekinyazilim.com/public_html/demo/nurskrom/" local="130209238180000000" remote="130368576600000000" Dst="1" />
<file name="he.php" server="ftp.ekinyazilim.com/public_html/demo/nurskrom/" local="130209238180000000" remote="130368576600000000" Dst="1" />
<file name="hi.php" server="ftp.ekinyazilim.com/public_html/demo/nurskrom/" local="130209238180000000" remote="130368576600000000" Dst="1" />
<file name="hr.php" server="ftp.ekinyazilim.com/public_html/demo/nurskrom/" local="130209238180000000" remote="130368576600000000" Dst="1" />
<file name="hu.php" server="ftp.ekinyazilim.com/public_html/demo/nurskrom/" local="130209238180000000" remote="130368576600000000" Dst="1" />
<file name="it.php" server="ftp.ekinyazilim.com/public_html/demo/nurskrom/" local="130209238180000000" remote="130368576600000000" Dst="1" />
<file name="ja.php" server="ftp.ekinyazilim.com/public_html/demo/nurskrom/" local="130209238180000000" remote="130368576600000000" Dst="1" />
<file name="lt.php" server="ftp.ekinyazilim.com/public_html/demo/nurskrom/" local="130209238180000000" remote="130368576600000000" Dst="1" />
<file name="lv.php" server="ftp.ekinyazilim.com/public_html/demo/nurskrom/" local="130209238180000000" remote="130368576600000000" Dst="1" />
<file name="nb.php" server="ftp.ekinyazilim.com/public_html/demo/nurskrom/" local="130209238180000000" remote="130368576600000000" Dst="1" />
<file name="nl.php" server="ftp.ekinyazilim.com/public_html/demo/nurskrom/" local="130209238180000000" remote="130368576600000000" Dst="1" />
<file name="nn.php" server="ftp.ekinyazilim.com/public_html/demo/nurskrom/" local="130209238180000000" remote="130368576600000000" Dst="1" />
<file name="no.php" server="ftp.ekinyazilim.com/public_html/demo/nurskrom/" local="130209238180000000" remote="130368576600000000" Dst="1" />
<file name="pl.php" server="ftp.ekinyazilim.com/public_html/demo/nurskrom/" local="130209238180000000" remote="130368576600000000" Dst="1" />
<file name="pt-br.php" server="ftp.ekinyazilim.com/public_html/demo/nurskrom/" local="130209238180000000" remote="130368576600000000" Dst="1" />
<file name="ro.php" server="ftp.ekinyazilim.com/public_html/demo/nurskrom/" local="130209238180000000" remote="130368576600000000" Dst="1" />
<file name="ru.php" server="ftp.ekinyazilim.com/public_html/demo/nurskrom/" local="130209238180000000" remote="130368576600000000" Dst="1" />
<file name="sk.php" server="ftp.ekinyazilim.com/public_html/demo/nurskrom/" local="130209238180000000" remote="130368576600000000" Dst="1" />
<file name="sl.php" server="ftp.ekinyazilim.com/public_html/demo/nurskrom/" local="130209238180000000" remote="130368576600000000" Dst="1" />
<file name="sr.php" server="ftp.ekinyazilim.com/public_html/demo/nurskrom/" local="130209238180000000" remote="130368576600000000" Dst="1" />
<file name="sv.php" server="ftp.ekinyazilim.com/public_html/demo/nurskrom/" local="130209238180000000" remote="130368576600000000" Dst="1" />
<file name="tr.php" server="ftp.ekinyazilim.com/public_html/demo/nurskrom/" local="130209238180000000" remote="130368576600000000" Dst="1" />
<file name="vi.php" server="ftp.ekinyazilim.com/public_html/demo/nurskrom/" local="130209238180000000" remote="130368576600000000" Dst="1" />
<file name="zh-cn.php" server="ftp.ekinyazilim.com/public_html/demo/nurskrom/" local="130209238180000000" remote="130368576600000000" Dst="1" />
<file name="zh-tw.php" server="ftp.ekinyazilim.com/public_html/demo/nurskrom/" local="130209238180000000" remote="130368576600000000" Dst="1" />
</dwsync>